kaiju_redis/__init__.py
kaiju_redis/services.py
kaiju_redis/tests/__init__.py
kaiju_redis/tests/fixtures.py
kaiju_redis/tests/test_cache.py
kaiju_redis/tests/test_redis.py
kaiju_redis-2.4.1.dist-info/licenses/LICENSE
kaiju_redis-2.4.1.dist-info/METADATA
kaiju_redis-2.4.1.dist-info/WHEEL
kaiju_redis-2.4.1.dist-info/top_level.txt
kaiju_redis-2.4.1.dist-info/RECORD
